commitizen_version_provider/__init__.py
kajihs_utils-0.10.3.dist-info/METADATA
kajihs_utils-0.10.3.dist-info/WHEEL
kajihs_utils-0.10.3.dist-info/entry_points.txt
kajihs_utils-0.10.3.dist-info/licenses/LICENSE
kajihs_utils-0.10.3.dist-info/RECORD
