Metadata-Version: 2.4
Name: kajihs-utils
Version: 0.10.3
Summary: Totally typed, plausibly practical, and remarkably random utilities—for me, and maybe for you too.
Project-URL: Repository, https://github.com/Kajiih/kajihs-utils
Project-URL: Homepage, https://github.com/Kajiih/kajihs-utils
Project-URL: Issues, https://github.com/Kajiih/kajihs-utils/issues
Project-URL: Changelog, https://github.com/Kajiih/kajihs-utils/blob/main/CHANGELOG.md
Project-URL: Documentation, https://Kajiih.github.io/kajihs-utils/
Author-email: Julian Paquerot <itskajih@gmail.com>
License-Expression: MIT
License-File: LICENSE
Keywords: jax,loguru,matplotlib,numpy,pyplot,python,tools,utils,whenever
Classifier: Development Status :: 3 - Alpha
Classifier: Intended Audience :: Developers
Classifier: License :: OSI Approved :: MIT License
Classifier: Natural Language :: English
Classifier: Operating System :: OS Independent
Classifier: Programming Language :: Python
Classifier: Programming Language :: Python :: 3 :: Only
Classifier: Programming Language :: Python :: 3.12
Classifier: Programming Language :: Python :: 3.13
Classifier: Programming Language :: Python :: 3.14
Classifier: Typing :: Typed
Requires-Python: >=3.12
Provides-Extra: jax
Requires-Dist: jax>=0.4.36; extra == 'jax'
Provides-Extra: loguru
Requires-Dist: loguru>=0.7.3; extra == 'loguru'
Requires-Dist: rich>=13.9.4; extra == 'loguru'
Provides-Extra: numpy
Requires-Dist: numpy>=2.2.0; extra == 'numpy'
Provides-Extra: pyplot
Requires-Dist: matplotlib>=3.10.0; extra == 'pyplot'
Provides-Extra: whenever
Requires-Dist: whenever>=0.7.3; extra == 'whenever'
